sbi_special_docx_master/__init__.py
sbi_special_docx_master/logger.py
sbi_special_docx_master/special_docx.py
sbi_special_docx_master/styles.py
sbi_special_docx_master/validator.py
sbi_special_docx_master-25.3.6.dist-info/licenses/LICENSE
tests/__init__.py
tests/spec_test.py
sbi_special_docx_master-25.3.6.dist-info/METADATA
sbi_special_docx_master-25.3.6.dist-info/WHEEL
sbi_special_docx_master-25.3.6.dist-info/top_level.txt
sbi_special_docx_master-25.3.6.dist-info/RECORD
