Metadata-Version: 2.4
Name: sbi_special_docx_master
Version: 25.3.6
Summary: A project for adding an information block to an MS .docx file
Author: Danila Aleksandrov
Author-email: danila.alexandrov24@gmail.com
Classifier: Intended Audience :: Developers
Classifier: Programming Language :: Python :: 3
Classifier: License :: OSI Approved :: MIT License
Classifier: Operating System :: OS Independent
Requires-Python: >=3.10
License-File: LICENSE
Requires-Dist: python-docx~=1.1.2
Requires-Dist: pydantic~=2.0
Requires-Dist: pillow~=11.1.0
Requires-Dist: pytest~=8.3.5
Provides-Extra: dev-deps
Requires-Dist: pytest; extra == "dev-deps"
Dynamic: author
Dynamic: author-email
Dynamic: classifier
Dynamic: description
Dynamic: description-content-type
Dynamic: license-file
Dynamic: provides-extra
Dynamic: requires-dist
Dynamic: requires-python
Dynamic: summary
